HISTORY.rst
LICENSE
MANIFEST.in
README.rst
setup.py
shell/__init__.py
shell/api.py
shell/compat.py
shell/input_stream.py
shell/parallel_api.py
shell/parallel_exec.py
shell/run_cmd.py
shell/util.py
shell.py.egg-info/PKG-INFO
shell.py.egg-info/SOURCES.txt
shell.py.egg-info/dependency_links.txt
shell.py.egg-info/not-zip-safe
shell.py.egg-info/top_level.txt