Metadata-Version: 1.1
Name: shell.py
Version: 0.4.0
Summary: Shell power for Python.
Home-page: https://github.com/houqp/shell.py
Author: Qingping Hou
Author-email: dave2008713@gmail.com
License: MIT
Platform: UNKNOWN
Classifier: Intended Audience :: Developers
Classifier: Natural Language :: English
Classifier: Programming Language :: Python
Classifier: Programming Language :: Python :: 2.6
Classifier: Programming Language :: Python :: 2.7
Classifier: Programming Language :: Python :: 3
Classifier: Programming Language :: Python :: 3.3
